dance/__init__.py
dance/config.py
dance/exceptions.py
dance/registers.py
dance/typing.py
dance/data/__init__.py
dance/data/base.py
dance/datasets/__init__.py
dance/datasets/base.py
dance/datasets/multimodality.py
dance/datasets/singlemodality.py
dance/datasets/spatial.py
dance/models/__init__.py
dance/models/nn/__init__.py
dance/models/nn/gnn.py
dance/models/nn/mlp.py
dance/modules/__init__.py
dance/modules/base.py
dance/modules/multi_modality/__init__.py
dance/modules/multi_modality/joint_embedding/__init__.py
dance/modules/multi_modality/joint_embedding/dcca.py
dance/modules/multi_modality/joint_embedding/jae.py
dance/modules/multi_modality/joint_embedding/scmogcn.py
dance/modules/multi_modality/joint_embedding/scmogcnv2.py
dance/modules/multi_modality/joint_embedding/scmvae.py
dance/modules/multi_modality/match_modality/__init__.py
dance/modules/multi_modality/match_modality/cmae.py
dance/modules/multi_modality/match_modality/scmm.py
dance/modules/multi_modality/match_modality/scmogcn.py
dance/modules/multi_modality/predict_modality/__init__.py
dance/modules/multi_modality/predict_modality/babel.py
dance/modules/multi_modality/predict_modality/cmae.py
dance/modules/multi_modality/predict_modality/scmm.py
dance/modules/multi_modality/predict_modality/scmogcn.py
dance/modules/single_modality/__init__.py
dance/modules/single_modality/cell_type_annotation/__init__.py
dance/modules/single_modality/cell_type_annotation/actinn.py
dance/modules/single_modality/cell_type_annotation/celltypist.py
dance/modules/single_modality/cell_type_annotation/scdeepsort.py
dance/modules/single_modality/cell_type_annotation/singlecellnet.py
dance/modules/single_modality/cell_type_annotation/svm.py
dance/modules/single_modality/clustering/__init__.py
dance/modules/single_modality/clustering/graphsc.py
dance/modules/single_modality/clustering/scdcc.py
dance/modules/single_modality/clustering/scdeepcluster.py
dance/modules/single_modality/clustering/scdsc.py
pydance-1.0.1.dist-info/METADATA
pydance-1.0.1.dist-info/WHEEL
pydance-1.0.1.dist-info/top_level.txt
pydance-1.0.1.dist-info/RECORD
