Metadata-Version: 2.1
Name: pydance
Version: 1.0.1
Summary: Deep Learning for Single-cell Analysis
Home-page: https://github.com/OmicsML/dance
Author: "DANCE Team"
Author-email: "danceteamgnn@gmail.com"
License: BSD 2-Clause License
Keywords: Single-cell Biology,Deep Learning,Graph Neural Networks
Platform: UNKNOWN
Classifier: Development Status :: 4 - Beta
Classifier: Programming Language :: Python
Classifier: Programming Language :: Python :: 3.8
Classifier: Programming Language :: Python :: 3.9
Classifier: Programming Language :: Python :: 3.10
Classifier: Programming Language :: Python :: 3.11
Classifier: Programming Language :: Python :: 3 :: Only
Requires-Python: >=3.8
Requires-Dist: h5py
Requires-Dist: igraph
Requires-Dist: leidenalg
Requires-Dist: louvain
Requires-Dist: mudata
Requires-Dist: networkx
Requires-Dist: numba
Requires-Dist: numpy
Requires-Dist: opencv-python
Requires-Dist: openpyxl
Requires-Dist: pandas
Requires-Dist: requests
Requires-Dist: scanpy
Requires-Dist: scib
Requires-Dist: scikit-learn
Requires-Dist: scikit-misc
Requires-Dist: scipy
Requires-Dist: statsmodels
Requires-Dist: tables
Requires-Dist: threadpoolctl (>=3.1.0)
Requires-Dist: tqdm
Provides-Extra: dev
Requires-Dist: pytest-subtests (==0.11.0) ; extra == 'dev'
Requires-Dist: pytest-xdist (==3.3.1) ; extra == 'dev'
Requires-Dist: pytest (==7.4.2) ; extra == 'dev'
Requires-Dist: pre-commit (==2.21.0) ; (python_version < "3.8") and extra == 'dev'
Requires-Dist: tox (==4.8.0) ; (python_version < "3.8") and extra == 'dev'
Requires-Dist: pre-commit (==3.5.0) ; (python_version >= "3.8") and extra == 'dev'
Requires-Dist: tox (==4.11.3) ; (python_version >= "3.8") and extra == 'dev'
Provides-Extra: doc
Requires-Dist: sphinx ; extra == 'doc'
Requires-Dist: sphinx-autodoc-typehints ; extra == 'doc'
Requires-Dist: sphinx-rtd-theme ; extra == 'doc'
Requires-Dist: sphinxcontrib-napoleon ; extra == 'doc'
